swarmstar/__init__.py
swarmstar/actions/__init__.py
swarmstar/actions/action_space.json
swarmstar/actions/coding/__init__.py
swarmstar/actions/coding/write_python.py
swarmstar/actions/communication/__init__.py
swarmstar/actions/communication/ask_user_questions.py
swarmstar/actions/reasoning/__init__.py
swarmstar/actions/reasoning/confirm_completion.py
swarmstar/actions/reasoning/decompose_directive.py
swarmstar/actions/reasoning/route_action.py
swarmstar/internal_metadata/action_space.sqlite3
swarmstar/memory/__init__.py
swarmstar/memory/memory_space_metadata.json
swarmstar/memory/swarm/__init__.py
swarmstar/memory/swarm/documentation/__init__.py
swarmstar/memory/swarm/documentation/configuration_chatbot.md
swarmstar/swarm/__init__.py
swarmstar/swarm/config.py
swarmstar/swarm/core.py
swarmstar/swarm/types/__init__.py
swarmstar/swarm/types/action_metadata.py
swarmstar/swarm/types/base_action.py
swarmstar/swarm/types/memory_metadata.py
swarmstar/swarm/types/swarm_config.py
swarmstar/swarm/types/swarm_history.py
swarmstar/swarm/types/swarm_nodes.py
swarmstar/swarm/types/swarm_operations.py
swarmstar/swarm/types/swarm_state.py
swarmstar/swarm/types/util_metadata.py
swarmstar/utils/__init__.py
swarmstar/utils/ai/__init__.py
swarmstar/utils/ai/openai_instructor.py
swarmstar/utils/data/__init__.py
swarmstar/utils/data/file_operations/__init__.py
swarmstar/utils/data/file_operations/azure_blob_storage.py
swarmstar/utils/data/file_operations/local_storage.py
swarmstar/utils/data/file_operations/main.py
swarmstar/utils/data/folder_operations/__init__.py
swarmstar/utils/data/folder_operations/azure_blob_storage.py
swarmstar/utils/data/folder_operations/local_storage.py
swarmstar/utils/data/folder_operations/main.py
swarmstar/utils/data/internal_operations.py
swarmstar/utils/data/kv_operations/__init__.py
swarmstar/utils/data/kv_operations/cosmos_db.py
swarmstar/utils/data/kv_operations/main.py
swarmstar/utils/data/kv_operations/mongodb.py
swarmstar-0.0.7.dist-info/LICENSE
swarmstar-0.0.7.dist-info/METADATA
swarmstar-0.0.7.dist-info/WHEEL
swarmstar-0.0.7.dist-info/RECORD
