Metadata-Version: 2.1
Name: swarmstar
Version: 0.0.7
Summary: 
Author: BrianP8701
Author-email: brianp8701@gmail.com
Requires-Python: >=3.10,<4.0
Classifier: Programming Language :: Python :: 3
Classifier: Programming Language :: Python :: 3.10
Classifier: Programming Language :: Python :: 3.11
Requires-Dist: azure-cosmos (>=4.5.1,<5.0.0)
Requires-Dist: azure-storage-blob (>=12.19.0,<13.0.0)
Requires-Dist: importlib (>=1.0.4,<2.0.0)
Requires-Dist: instructor (>=0.4.8,<0.5.0)
Requires-Dist: openai (>=1.9.0,<2.0.0)
Requires-Dist: pydantic (>=2.5.3,<3.0.0)
Requires-Dist: pymongo (>=4.6.1,<5.0.0)
Project-URL: Documentation, https://brianp8701.github.io/swarmstar/
